zest/__init__.py
zest/all_tests.py
zest/tests.py
zest/utility.py
zest-0.1.1.post1.dist-info/METADATA
zest-0.1.1.post1.dist-info/WHEEL
zest-0.1.1.post1.dist-info/top_level.txt
zest-0.1.1.post1.dist-info/RECORD
