Metadata-Version: 2.1
Name: zest
Version: 0.1.1.post1
Summary: A testing utility package
Home-page: https://github.com/jezza672/zest
Author: Jeremy Zolnai-Lucas
Author-email: jezza672@gmail.com
License: UNKNOWN
Platform: UNKNOWN
Classifier: Programming Language :: Python :: 3
Classifier: License :: OSI Approved :: MIT License
Classifier: Operating System :: OS Independent
